{"measures":[{"name":"sdk:pre-test","entryType":"measure","startTime":764.943458,"duration":3.7204169999999976,"detail":null,"success":true,"failure":null,"worker":"3920-0"},{"name":"sdk:hook","entryType":"measure","startTime":773.75225,"duration":0.23987499999998363,"detail":null,"success":true,"failure":null,"worker":"3920-0","testName":"test-image-loading.spec.js - all shelf items should have an image [TC-1930]","hookType":"beforeTestHook"},{"name":"sdk:o11y:sync","entryType":"measure","startTime":8476.135042,"duration":186.15662499999962,"detail":null,"success":true,"failure":null,"worker":"3920-0","testName":"test-image-loading.spec.js - all shelf items should have an image [TC-1930]"},{"name":"sdk:automate:session-annotation","entryType":"measure","startTime":8476.395292,"duration":185.6755830000002,"detail":null,"success":true,"failure":null,"worker":"3920-0","testName":"test-image-loading.spec.js - all shelf items should have an image [TC-1930]"},{"name":"sdk:automate:session-annotation","entryType":"measure","startTime":8476.395292,"duration":573.5475830000014,"detail":null,"success":true,"failure":null,"worker":"3920-0","testName":"test-image-loading.spec.js - all shelf items should have an image [TC-1930]"},{"name":"sdk:automate:session-name","entryType":"measure","startTime":8663.312125,"duration":386.84612500000003,"detail":null,"success":true,"failure":null,"worker":"3920-0","testName":"test-image-loading.spec.js - all shelf items should have an image [TC-1930]"},{"name":"sdk:o11y:driver-takeScreenShot","entryType":"measure","startTime":24124.873667,"duration":0.6774580000019341,"detail":null,"success":true,"failure":null,"worker":"3920-0","testName":"test-image-loading.spec.js - all shelf items should have an image [TC-1930]"},{"name":"sdk:o11y:sync","entryType":"measure","startTime":8476.135042,"duration":16808.871041,"detail":null,"success":true,"failure":null,"worker":"3920-0","testName":"test-image-loading.spec.js - all shelf items should have an image [TC-1930]"},{"name":"sdk:automate:session-annotation","entryType":"measure","startTime":8476.395292,"duration":16808.487375000004,"detail":null,"success":true,"failure":null,"worker":"3920-0","testName":"test-image-loading.spec.js - all shelf items should have an image [TC-1930]"},{"name":"sdk:hook","entryType":"measure","startTime":773.75225,"duration":24912.460333,"detail":null,"success":true,"failure":null,"worker":"3920-0","testName":"test-image-loading.spec.js - all shelf items should have an image [TC-1930]","hookType":"afterTestHook"},{"name":"sdk:automate:session-annotation","entryType":"measure","startTime":8476.395292,"duration":17209.589083,"detail":null,"success":true,"failure":null,"worker":"3920-0","testName":"test-image-loading.spec.js - all shelf items should have an image [TC-1930]"},{"name":"sdk:automate:session-name","entryType":"measure","startTime":8663.312125,"duration":17022.795208,"detail":null,"success":true,"failure":null,"worker":"3920-0","testName":"test-image-loading.spec.js - all shelf items should have an image [TC-1930]"},{"name":"sdk:post-test","entryType":"measure","startTime":25063.508292,"duration":622.7401250000003,"detail":null,"success":true,"failure":null,"worker":"3920-0","testName":"test-image-loading.spec.js - all shelf items should have an image [TC-1930]"},{"name":"sdk:automate:session-annotation","entryType":"measure","startTime":8476.395292,"duration":17446.320165999998,"detail":null,"success":true,"failure":null,"worker":"3920-0","testName":"test-image-loading.spec.js - all shelf items should have an image [TC-1930]"},{"name":"sdk:test","entryType":"measure","startTime":773.083167,"duration":25667.0855,"detail":null,"success":true,"failure":null,"worker":"3920-0","testName":"test-image-loading.spec.js - all shelf items should have an image [TC-1930]"},{"name":"sdk:hook","entryType":"measure","startTime":773.75225,"duration":25664.485916999998,"detail":null,"success":true,"failure":null,"worker":"3920-0","testName":"test-image-loading.spec.js - all shelf items should have an image [TC-1930]","hookType":"afterTestHook"},{"name":"sdk:automate:session-annotation","entryType":"measure","startTime":8476.395292,"duration":17961.736750000004,"detail":null,"success":true,"failure":null,"worker":"3920-0","testName":"test-image-loading.spec.js - all shelf items should have an image [TC-1930]"},{"name":"sdk:post-test","entryType":"measure","startTime":25063.508292,"duration":1374.744708000002,"detail":null,"success":true,"failure":null,"worker":"3920-0","testName":"test-image-loading.spec.js - all shelf items should have an image [TC-1930]"},{"name":"sdk:automate:session-status","entryType":"measure","startTime":25922.93975,"duration":515.2588329999999,"detail":null,"success":true,"failure":null,"worker":"3920-0","testName":"test-image-loading.spec.js - all shelf items should have an image [TC-1930]"},{"name":"sdk:testhub","entryType":"measure","startTime":167.98841601610184,"duration":1674.8542090058327,"detail":null,"success":true,"failure":null,"worker":3066},{"name":"sdk:percy","entryType":"measure","startTime":1848.377041041851,"duration":0.250124990940094,"detail":null,"success":true,"failure":null,"worker":3066},{"name":"sdk:automate:local","entryType":"measure","startTime":1848.7050830125809,"duration":0.14158302545547485,"detail":null,"success":true,"failure":null,"worker":3066},{"name":"sdk:automate:hub-management","entryType":"measure","startTime":3189.7479580044746,"duration":1447.898582994938,"detail":null,"success":true,"failure":null,"worker":3066},{"name":"sdk:automate:print-buildlink","entryType":"measure","startTime":89976.4096249938,"duration":1824.182666003704,"detail":null,"success":true,"failure":null,"worker":3066},{"name":"sdk:proxy-setup","entryType":"measure","startTime":727.9945,"duration":0.06758300000001327,"detail":null,"success":true,"failure":null,"worker":"3030-0"},{"name":"sdk:automate:keep-alive","entryType":"measure","startTime":728.593958,"duration":0.08795799999995779,"detail":null,"success":true,"failure":null,"worker":"3030-0"},{"name":"request:https://hub.browserstack.com/next_hubs","entryType":"measure","startTime":729.265791,"duration":1378.6572089999997,"detail":null,"success":true,"failure":null,"worker":"3030-0"},{"name":"request:https://api.browserstack.com/sdk/v1/event","entryType":"measure","startTime":727.565458,"duration":1693.9627500000001,"detail":null,"success":true,"failure":null,"worker":"3030-0"},{"name":"request:https://hub-euw.browserstack.com/check","entryType":"measure","startTime":2108.2395,"duration":725.6030409999998,"detail":null,"success":true,"failure":null,"worker":"3030-0"},{"name":"request:https://hub-aps.browserstack.com/check","entryType":"measure","startTime":2108.304958,"duration":1631.8576249999996,"detail":null,"success":true,"failure":null,"worker":"3030-0"},{"name":"sdk:automate:hub-management","entryType":"measure","startTime":729.13225,"duration":3064.491583,"detail":null,"success":true,"failure":null,"worker":"3030-0"},{"name":"request:https://hub-use.browserstack.com/check","entryType":"measure","startTime":2108.272375,"duration":1684.687958,"detail":null,"success":true,"failure":null,"worker":"3030-0"},{"name":"sdk:cli:check-update","entryType":"measure","startTime":3797.955416,"duration":683.3141249999999,"detail":null,"success":true,"failure":null,"worker":"3030-0"},{"name":"request:https://api.browserstack.com/sdk/v1/update_cli","entryType":"measure","startTime":4164.277958,"duration":316.46500000000015,"detail":null,"success":true,"failure":null,"worker":"3030-0"},{"name":"sdk:cli:start","entryType":"measure","startTime":3795.384916,"duration":861.6722920000002,"detail":null,"success":true,"failure":null,"worker":"3030-0"},{"name":"sdk:setup","entryType":"measure","startTime":671.635625,"duration":5734.201625,"detail":null,"success":true,"failure":null,"worker":"3030-0"},{"name":"sdk:driver:pre-initialization","entryType":"measure","startTime":683.182041,"duration":5724.30325,"detail":null,"success":true,"failure":null,"worker":"3030-0"},{"name":"sdk:startBinSession","entryType":"measure","startTime":4657.259833,"duration":1733.2903749999996,"detail":null,"success":true,"failure":null,"worker":"3030-0"},{"name":"sdk:driver:post-initialization","entryType":"measure","startTime":6401.975541,"duration":0.21512500000062573,"detail":null,"success":true,"failure":null,"worker":"3030-0"},{"name":"sdk:testhub:stop","entryType":"measure","startTime":89211.061875,"duration":1.0661249999975553,"detail":null,"success":true,"failure":null,"worker":"3030-0"},{"name":"sdk:cli:on-stop","entryType":"measure","startTime":89212.7055,"duration":8279.638707999999,"detail":null,"success":true,"failure":null,"worker":"3030-0"},{"name":"sdk:cli:on-stop","entryType":"measure","startTime":89212.7055,"duration":13305.440375000006,"detail":null,"success":true,"failure":null,"worker":"3030-0"},{"name":"sdk:o11y:print-buildlink","entryType":"measure","startTime":102519.020333,"duration":1.4147920000104932,"detail":null,"success":true,"failure":null,"worker":"3030-0"},{"name":"sdk:automate:print-buildlink","entryType":"measure","startTime":102520.88825,"duration":845.979582999993,"detail":null,"success":true,"failure":null,"worker":"3030-0"},{"name":"request:https://api.browserstack.com/automate/builds.json","entryType":"measure","startTime":102521.227041,"duration":844.7302090000012,"detail":null,"success":true,"failure":null,"worker":"3030-0"},{"name":"request:https://api.browserstack.com/sdk/v1/event","entryType":"measure","startTime":727.565458,"duration":103025.923625,"detail":null,"success":true,"failure":null,"worker":"3030-0"},{"name":"request:https://upload-observability.browserstack.com/client-logs/upload","entryType":"measure","startTime":103769.939208,"duration":7152.449417000011,"detail":null,"success":true,"failure":null,"worker":"3030-0"},{"name":"sdk:auto-capture","entryType":"measure","startTime":103754.286166,"duration":7169.416459,"detail":null,"success":true,"failure":null,"worker":"3030-0"},{"name":"sdk:cleanup","entryType":"measure","startTime":6407.505958,"duration":104643.95945800001,"detail":null,"success":true,"failure":null,"worker":"3030-0"},{"name":"sdk:testhub:stop","entryType":"measure","startTime":89211.061875,"duration":21840.259833000004,"detail":null,"success":true,"failure":null,"worker":"3030-0"}],"exceptions":[],"sdkRunId":"5b78b42a-b0bc-434e-a63c-6f4098425945"}